ocr_translate_tesseract/__init__.py
ocr_translate_tesseract/plugin.py
ocr_translate_tesseract-0.4.0.dist-info/entry_points.txt
ocr_translate_tesseract-0.4.0.dist-info/licenses/LICENSE.txt
ocr_translate_tesseract-0.4.0.dist-info/WHEEL
ocr_translate_tesseract-0.4.0.dist-info/METADATA
ocr_translate_tesseract-0.4.0.dist-info/RECORD
